Metadata-Version: 2.1
Name: sorting-array-package
Version: 0.4
Summary: selection sort
Author: Quirrel
Author-email: symmlux@gmail.com
License: MIT License
Requires-Python: >=3.5
License-File: LICENSE.txt
